pyoneclick-0.0.7.dist-info/licenses/LICENSE.txt
src/__init__.py
src/main.py
src/stata_config.py
pyoneclick-0.0.7.dist-info/METADATA
pyoneclick-0.0.7.dist-info/WHEEL
pyoneclick-0.0.7.dist-info/entry_points.txt
pyoneclick-0.0.7.dist-info/top_level.txt
pyoneclick-0.0.7.dist-info/RECORD
