Metadata-Version: 2.4
Name: pyoneclick
Version: 0.0.7
Summary: This tool enables the automatic screening of control variables to adjust the significance of specific variables, similar to Stata's 'oneclick' command, while offering enhanced functionality.
Author: zpjbtdjm
Classifier: Programming Language :: Python :: 3
Classifier: License :: OSI Approved :: MIT License
Classifier: Operating System :: Microsoft :: Windows
License-File: LICENSE.txt
Requires-Dist: stata_setup
Requires-Dist: tqdm
Dynamic: author
Dynamic: classifier
Dynamic: description
Dynamic: description-content-type
Dynamic: license-file
Dynamic: requires-dist
Dynamic: summary
